bd_shape_history/__init__.py
bd_shape_history/cli.py
bd_shape_history/shape_history.py
bd_shape_history/step.py
bd_shape_history/types.py
bd_shape_history-0.1.1.dist-info/LICENSE
bd_shape_history-0.1.1.dist-info/METADATA
bd_shape_history-0.1.1.dist-info/WHEEL
bd_shape_history-0.1.1.dist-info/entry_points.txt
bd_shape_history-0.1.1.dist-info/RECORD
