Metadata-Version: 2.1
Name: bd_shape_history
Version: 0.1.1
Summary: A tool to manage and visualize the modification history of Build123D objects.
Home-page: https://codeberg.org/roipoussiere/bd_shape_history
License: MIT
Keywords: cad,build123d,history
Author: Nathanaël Jourdane
Author-email: njourdane@protonmail.com
Requires-Python: >=3.11,<3.13
Classifier: Development Status :: 4 - Beta
Classifier: Intended Audience :: Manufacturing
Classifier: License :: OSI Approved :: MIT License
Classifier: Operating System :: OS Independent
Classifier: Programming Language :: Python :: 3
Classifier: Programming Language :: Python :: 3.11
Classifier: Programming Language :: Python :: 3.12
Classifier: Topic :: Multimedia :: Graphics :: 3D Modeling
Classifier: Topic :: Scientific/Engineering
Classifier: Topic :: Software Development :: Debuggers
Requires-Dist: cadquery-ocp (>=7.7.2,<8.0.0)
Requires-Dist: ocp-tessellate (>=3.0.8,<4.0.0)
Requires-Dist: ocp-vscode (>=2.6.1,<3.0.0)
Project-URL: Repository, https://codeberg.org/roipoussiere/bd_shape_history
